svglib/__init__.py
svglib/fonts.py
svglib/svglib.py
svglib/utils.py
svglibwheel-0.1.data/data/share/man/man1/svg2pdf.1
svglibwheel-0.1.data/scripts/svg2pdf
svglibwheel-0.1.dist-info/LICENSE.txt
svglibwheel-0.1.dist-info/METADATA
svglibwheel-0.1.dist-info/WHEEL
svglibwheel-0.1.dist-info/top_level.txt
svglibwheel-0.1.dist-info/RECORD
