Metadata-Version: 2.1
Name: svglibwheel
Version: 0.1
Summary: A pure-Python library for reading and converting SVG
Home-page: https://github.com/deeplook/svglib
Author: Dinu Gherman
Author-email: gherman@darwin.in-berlin.de
License: LGPL 3
Keywords: SVG,PDF,reportlab,conversion,graphics
Classifier: Development Status :: 5 - Production/Stable
Classifier: Environment :: Console
Classifier: Intended Audience :: End Users/Desktop
Classifier: Intended Audience :: Developers
Classifier: License :: OSI Approved :: GNU Lesser General Public License v3 (LGPLv3)
Classifier: Operating System :: MacOS :: MacOS X
Classifier: Operating System :: Microsoft :: Windows
Classifier: Operating System :: POSIX
Classifier: Natural Language :: English
Classifier: Programming Language :: Python
Classifier: Programming Language :: Python :: 3.8
Classifier: Programming Language :: Python :: 3.9
Classifier: Programming Language :: Python :: 3.10
Classifier: Programming Language :: Python :: 3.11
Classifier: Programming Language :: Python :: 3 :: Only
Classifier: Topic :: Documentation
Classifier: Topic :: Utilities
Classifier: Topic :: Printing
Classifier: Topic :: Multimedia :: Graphics :: Graphics Conversion
Classifier: Topic :: Software Development :: Libraries :: Python Modules
Classifier: Topic :: Text Processing :: Markup :: XML
Requires-Python: >=3.8
License-File: LICENSE.txt
Requires-Dist: reportlab
Requires-Dist: lxml
Requires-Dist: tinycss2 >=0.6.0
Requires-Dist: cssselect2 >=0.2.0
